Metadata-Version: 2.1
Name: IMAtoDICOMImage
Version: 1.0.0
Summary: IMA converter
Home-page: UNKNOWN
Author: Maryam Oghbaei
Author-email: maryam.oghbayi@gmail.com
License: UNKNOWN
Platform: UNKNOWN
Classifier: License :: OSI Approved :: MIT License
Classifier: Programming Language :: Python :: 3
Classifier: Programming Language :: Python :: 3.6
Classifier: Programming Language :: Python :: 3.7
Classifier: Programming Language :: Python :: 3.8
Classifier: Programming Language :: Python :: 3.9
Classifier: Programming Language :: Python :: 3.10
Classifier: Operating System :: OS Independent
Requires-Python: >=3.6
